centrifuge/__init__.py
centrifuge/__meta__.py
centrifuge/client.py
centrifuge/codecs.py
centrifuge/codes.py
centrifuge/contexts.py
centrifuge/exceptions.py
centrifuge/fossil.py
centrifuge/handlers.py
centrifuge/types.py
centrifuge/utils.py
centrifuge/protocol/__init__.py
centrifuge/protocol/client_pb2.py
centrifuge_python-0.4.2.dist-info/METADATA
centrifuge_python-0.4.2.dist-info/WHEEL
centrifuge_python-0.4.2.dist-info/licenses/LICENSE
centrifuge_python-0.4.2.dist-info/RECORD
