Metadata-Version: 2.4
Name: centrifuge-python
Version: 0.4.2
Summary: WebSocket SDK for Centrifugo (and any Centrifuge-based server) on top of Python asyncio library
Author: Alexander Emelin (Centrifugal Labs LTD), Katant Savelev
License-Expression: MIT
License-File: LICENSE
Keywords: Centrifuge,Centrifugo,Pub/Sub,Realtime,WebSocket
Classifier: Development Status :: 4 - Beta
Classifier: Framework :: AsyncIO
Classifier: Intended Audience :: Developers
Classifier: Intended Audience :: Information Technology
Classifier: License :: OSI Approved :: MIT License
Classifier: Operating System :: OS Independent
Classifier: Programming Language :: Python
Classifier: Programming Language :: Python :: 3
Classifier: Programming Language :: Python :: 3 :: Only
Classifier: Programming Language :: Python :: 3.9
Classifier: Programming Language :: Python :: 3.10
Classifier: Programming Language :: Python :: 3.11
Classifier: Programming Language :: Python :: 3.12
Classifier: Programming Language :: Python :: 3.13
Classifier: Topic :: Internet
Classifier: Topic :: Software Development :: Libraries :: Python Modules
Classifier: Topic :: System :: Networking
Classifier: Typing :: Typed
Requires-Python: >=3.9
Requires-Dist: protobuf<7.0.0,>=4.23.4
Requires-Dist: websockets<16.0.0,>=14.0.0
Provides-Extra: dev
Requires-Dist: pre-commit~=3.5.0; extra == 'dev'
Requires-Dist: ruff~=0.1.4; extra == 'dev'
